{
  "updated": "2025-10-13T01:10:09.572Z",
  "domains": [
    {
      "d": "zvi.cl",
      "date": "2025-10-12T22:08:43Z"
    },
    {
      "d": "cometelotodo.cl",
      "date": "2025-10-12T22:05:15Z"
    },
    {
      "d": "centromedicointegralrapport.cl",
      "date": "2025-10-12T22:02:05Z"
    },
    {
      "d": "rycelectric.cl",
      "date": "2025-10-12T21:59:14Z"
    },
    {
      "d": "manosconstructoras.cl",
      "date": "2025-10-12T21:55:21Z"
    },
    {
      "d": "vistealuna.cl",
      "date": "2025-10-12T21:50:34Z"
    },
    {
      "d": "electrocomercialservicios.cl",
      "date": "2025-10-12T21:49:39Z"
    },
    {
      "d": "redeselectricas.cl",
      "date": "2025-10-12T21:49:08Z"
    },
    {
      "d": "defensaydeudas.cl",
      "date": "2025-10-12T21:45:14Z"
    },
    {
      "d": "generacionelectrica.cl",
      "date": "2025-10-12T21:43:57Z"
    },
    {
      "d": "tallerdelvikingo.cl",
      "date": "2025-10-12T21:35:23Z"
    },
    {
      "d": "sbs-skin-beauty-store.cl",
      "date": "2025-10-12T21:30:14Z"
    },
    {
      "d": "ggconsultores.cl",
      "date": "2025-10-12T21:29:18Z"
    },
    {
      "d": "distribucionelectrica.cl",
      "date": "2025-10-12T21:25:44Z"
    },
    {
      "d": "oxytane.cl",
      "date": "2025-10-12T21:25:09Z"
    },
    {
      "d": "ironhost.cl",
      "date": "2025-10-12T21:24:02Z"
    },
    {
      "d": "transmisionelectrica.cl",
      "date": "2025-10-12T21:20:21Z"
    },
    {
      "d": "marketinglab360.cl",
      "date": "2025-10-12T21:12:12Z"
    },
    {
      "d": "mundosublimacion-transfer.cl",
      "date": "2025-10-12T21:07:53Z"
    },
    {
      "d": "calculoselectricos.cl",
      "date": "2025-10-12T21:05:38Z"
    },
    {
      "d": "silhouettecameo-chile.cl",
      "date": "2025-10-12T21:04:09Z"
    },
    {
      "d": "finanzasdelfuturo.cl",
      "date": "2025-10-12T21:00:09Z"
    },
    {
      "d": "multimetro.cl",
      "date": "2025-10-12T20:59:06Z"
    },
    {
      "d": "blendhouse.cl",
      "date": "2025-10-12T20:59:02Z"
    },
    {
      "d": "seirendojo.cl",
      "date": "2025-10-12T20:58:44Z"
    },
    {
      "d": "zendoapp.cl",
      "date": "2025-10-12T20:55:02Z"
    },
    {
      "d": "radiodisfrutame.cl",
      "date": "2025-10-12T20:48:24Z"
    },
    {
      "d": "aristoteliaelixir.cl",
      "date": "2025-10-12T20:38:51Z"
    },
    {
      "d": "acmr.cl",
      "date": "2025-10-12T20:38:35Z"
    },
    {
      "d": "tourcuatrimoto.cl",
      "date": "2025-10-12T20:30:47Z"
    },
    {
      "d": "educacioninmversiva.cl",
      "date": "2025-10-12T20:25:56Z"
    },
    {
      "d": "zullinka.cl",
      "date": "2025-10-12T20:25:44Z"
    },
    {
      "d": "kaleiscapital.cl",
      "date": "2025-10-12T20:21:50Z"
    },
    {
      "d": "kaleis.cl",
      "date": "2025-10-12T20:21:49Z"
    },
    {
      "d": "toptop.cl",
      "date": "2025-10-12T20:21:03Z"
    },
    {
      "d": "preuniversitarioortegapinto.cl",
      "date": "2025-10-12T20:17:38Z"
    },
    {
      "d": "lasonoradetommyreyoficial.cl",
      "date": "2025-10-12T20:15:07Z"
    },
    {
      "d": "veraluztienda.cl",
      "date": "2025-10-12T20:12:49Z"
    },
    {
      "d": "sirec.cl",
      "date": "2025-10-12T20:06:53Z"
    },
    {
      "d": "deninfa.cl",
      "date": "2025-10-12T20:00:07Z"
    },
    {
      "d": "joyasenlaciudad.cl",
      "date": "2025-10-12T19:59:15Z"
    },
    {
      "d": "agenciapacificosur.cl",
      "date": "2025-10-12T19:48:10Z"
    },
    {
      "d": "gomove.cl",
      "date": "2025-10-12T19:47:37Z"
    },
    {
      "d": "aurinn.cl",
      "date": "2025-10-12T19:45:34Z"
    },
    {
      "d": "gestiondeproyectos.cl",
      "date": "2025-10-12T19:43:44Z"
    },
    {
      "d": "liongrow.cl",
      "date": "2025-10-12T19:32:33Z"
    },
    {
      "d": "psechile.cl",
      "date": "2025-10-12T19:30:56Z"
    },
    {
      "d": "grupp.cl",
      "date": "2025-10-12T19:25:29Z"
    },
    {
      "d": "hunterwolf.cl",
      "date": "2025-10-12T19:24:41Z"
    },
    {
      "d": "comminerspa.cl",
      "date": "2025-10-12T19:22:29Z"
    },
    {
      "d": "d3vs.cl",
      "date": "2025-10-12T19:22:27Z"
    },
    {
      "d": "induverso.cl",
      "date": "2025-10-12T19:20:34Z"
    },
    {
      "d": "safebike.cl",
      "date": "2025-10-12T19:19:03Z"
    },
    {
      "d": "miningclass.cl",
      "date": "2025-10-12T19:17:32Z"
    },
    {
      "d": "perrosenior.cl",
      "date": "2025-10-12T19:13:27Z"
    },
    {
      "d": "prosigna.cl",
      "date": "2025-10-12T19:13:14Z"
    },
    {
      "d": "ellass.cl",
      "date": "2025-10-12T19:08:16Z"
    },
    {
      "d": "umind.cl",
      "date": "2025-10-12T18:58:10Z"
    },
    {
      "d": "vvstore.cl",
      "date": "2025-10-12T18:56:21Z"
    },
    {
      "d": "divorciosenchile.cl",
      "date": "2025-10-12T18:55:43Z"
    },
    {
      "d": "chakolab.cl",
      "date": "2025-10-12T18:47:27Z"
    },
    {
      "d": "monicaboutique.cl",
      "date": "2025-10-12T18:37:20Z"
    },
    {
      "d": "abcontabilidad.cl",
      "date": "2025-10-12T18:28:11Z"
    },
    {
      "d": "cuidarnos.cl",
      "date": "2025-10-12T18:17:47Z"
    },
    {
      "d": "hosteriakathalina.cl",
      "date": "2025-10-12T18:17:10Z"
    },
    {
      "d": "nawelgroup.cl",
      "date": "2025-10-12T18:17:07Z"
    },
    {
      "d": "huellachic.cl",
      "date": "2025-10-12T18:15:04Z"
    },
    {
      "d": "rodrigoramos.cl",
      "date": "2025-10-12T18:11:53Z"
    },
    {
      "d": "vamosbohemias.cl",
      "date": "2025-10-12T18:10:51Z"
    },
    {
      "d": "arprevencionlegal.cl",
      "date": "2025-10-12T18:10:43Z"
    },
    {
      "d": "detonadas.cl",
      "date": "2025-10-12T17:54:34Z"
    },
    {
      "d": "hojalateriamiguelcorrea.cl",
      "date": "2025-10-12T17:52:53Z"
    },
    {
      "d": "indieschileweek.cl",
      "date": "2025-10-12T17:47:22Z"
    },
    {
      "d": "bmconsultoresjuridicos.cl",
      "date": "2025-10-12T17:47:04Z"
    },
    {
      "d": "phra.cl",
      "date": "2025-10-12T17:46:22Z"
    },
    {
      "d": "ventilaire.cl",
      "date": "2025-10-12T17:44:14Z"
    },
    {
      "d": "lumicare.cl",
      "date": "2025-10-12T17:42:06Z"
    },
    {
      "d": "ruta4.cl",
      "date": "2025-10-12T17:38:20Z"
    },
    {
      "d": "nicolecontadora.cl",
      "date": "2025-10-12T17:34:39Z"
    },
    {
      "d": "dogabo.cl",
      "date": "2025-10-12T17:32:20Z"
    },
    {
      "d": "frao.cl",
      "date": "2025-10-12T17:29:04Z"
    },
    {
      "d": "invertum.cl",
      "date": "2025-10-12T17:21:55Z"
    },
    {
      "d": "qmcingenieria.cl",
      "date": "2025-10-12T17:21:13Z"
    },
    {
      "d": "afiladoexpress.cl",
      "date": "2025-10-12T17:12:44Z"
    },
    {
      "d": "siddo.cl",
      "date": "2025-10-12T17:10:14Z"
    },
    {
      "d": "tintaerrante.cl",
      "date": "2025-10-12T17:07:06Z"
    },
    {
      "d": "pulentavida.cl",
      "date": "2025-10-12T17:02:27Z"
    },
    {
      "d": "premaseg.cl",
      "date": "2025-10-12T16:57:20Z"
    },
    {
      "d": "qakiinis.cl",
      "date": "2025-10-12T16:55:32Z"
    },
    {
      "d": "danviship.cl",
      "date": "2025-10-12T16:50:55Z"
    },
    {
      "d": "mgcomercializadora.cl",
      "date": "2025-10-12T16:46:34Z"
    },
    {
      "d": "tiendaciclos.cl",
      "date": "2025-10-12T16:45:23Z"
    },
    {
      "d": "klonchile.cl",
      "date": "2025-10-12T16:38:55Z"
    },
    {
      "d": "jcontreras.cl",
      "date": "2025-10-12T16:37:52Z"
    },
    {
      "d": "fortfoods.cl",
      "date": "2025-10-12T16:26:09Z"
    },
    {
      "d": "maxago.cl",
      "date": "2025-10-12T16:22:00Z"
    },
    {
      "d": "solucioneszimbi.cl",
      "date": "2025-10-12T16:15:37Z"
    },
    {
      "d": "conciencianutritiva.cl",
      "date": "2025-10-12T16:15:20Z"
    },
    {
      "d": "rivaida.cl",
      "date": "2025-10-12T16:12:10Z"
    },
    {
      "d": "anata.cl",
      "date": "2025-10-12T16:10:50Z"
    },
    {
      "d": "kuspide.cl",
      "date": "2025-10-12T16:10:39Z"
    },
    {
      "d": "todovegano.cl",
      "date": "2025-10-12T16:03:55Z"
    },
    {
      "d": "leisure.cl",
      "date": "2025-10-12T15:56:54Z"
    },
    {
      "d": "sopravalfoods.cl",
      "date": "2025-10-12T15:55:55Z"
    },
    {
      "d": "diatza.cl",
      "date": "2025-10-12T15:43:48Z"
    },
    {
      "d": "jueza.cl",
      "date": "2025-10-12T15:42:53Z"
    },
    {
      "d": "exploraene.cl",
      "date": "2025-10-12T15:41:46Z"
    },
    {
      "d": "elrincondepepelucho.cl",
      "date": "2025-10-12T15:39:12Z"
    },
    {
      "d": "pausacreativa.cl",
      "date": "2025-10-12T15:33:47Z"
    },
    {
      "d": "infinitysolutions.cl",
      "date": "2025-10-12T15:33:10Z"
    },
    {
      "d": "cesarcastillo.cl",
      "date": "2025-10-12T15:26:51Z"
    },
    {
      "d": "miyane.cl",
      "date": "2025-10-12T15:22:56Z"
    },
    {
      "d": "tramitaconmigo.cl",
      "date": "2025-10-12T15:22:50Z"
    },
    {
      "d": "rst.cl",
      "date": "2025-10-12T15:17:41Z"
    },
    {
      "d": "radiofmtop.cl",
      "date": "2025-10-12T15:16:35Z"
    },
    {
      "d": "danielitaimpresiones.cl",
      "date": "2025-10-12T15:04:23Z"
    },
    {
      "d": "boxmo.cl",
      "date": "2025-10-12T15:02:16Z"
    },
    {
      "d": "olivachia.cl",
      "date": "2025-10-12T15:00:30Z"
    },
    {
      "d": "oilchia.cl",
      "date": "2025-10-12T15:00:29Z"
    },
    {
      "d": "chiaoliva.cl",
      "date": "2025-10-12T15:00:28Z"
    },
    {
      "d": "aceitedechia.cl",
      "date": "2025-10-12T15:00:27Z"
    },
    {
      "d": "aceitepepitadeuva.cl",
      "date": "2025-10-12T15:00:26Z"
    },
    {
      "d": "pepitadeuva.cl",
      "date": "2025-10-12T15:00:25Z"
    },
    {
      "d": "hysa.cl",
      "date": "2025-10-12T14:50:28Z"
    },
    {
      "d": "marinacommerce.cl",
      "date": "2025-10-12T14:45:05Z"
    },
    {
      "d": "vitrostudio.cl",
      "date": "2025-10-12T14:43:13Z"
    },
    {
      "d": "3vmcorp.cl",
      "date": "2025-10-12T14:42:02Z"
    },
    {
      "d": "3vmcorp-latam.cl",
      "date": "2025-10-12T14:42:01Z"
    },
    {
      "d": "estudios-mjvec.cl",
      "date": "2025-10-12T14:34:03Z"
    },
    {
      "d": "ivacadenza.cl",
      "date": "2025-10-12T14:27:42Z"
    },
    {
      "d": "terra-travel.cl",
      "date": "2025-10-12T14:23:25Z"
    },
    {
      "d": "elcaminodepirque.cl",
      "date": "2025-10-12T14:04:59Z"
    },
    {
      "d": "bioeco.cl",
      "date": "2025-10-12T14:04:46Z"
    },
    {
      "d": "tapti.cl",
      "date": "2025-10-12T13:59:34Z"
    },
    {
      "d": "un-nuevo-natales.cl",
      "date": "2025-10-12T13:57:05Z"
    },
    {
      "d": "sudamericanhackers.cl",
      "date": "2025-10-12T13:54:14Z"
    },
    {
      "d": "agenciaecheverria.cl",
      "date": "2025-10-12T13:50:50Z"
    },
    {
      "d": "etycc.cl",
      "date": "2025-10-12T13:42:11Z"
    },
    {
      "d": "tosusanagonzalez.cl",
      "date": "2025-10-12T13:35:30Z"
    },
    {
      "d": "graciacg.cl",
      "date": "2025-10-12T13:20:48Z"
    },
    {
      "d": "graciaconsulting.cl",
      "date": "2025-10-12T13:20:47Z"
    },
    {
      "d": "mejoratuisapre.cl",
      "date": "2025-10-12T13:20:07Z"
    },
    {
      "d": "karlibeauty.cl",
      "date": "2025-10-12T13:17:37Z"
    },
    {
      "d": "syloma.cl",
      "date": "2025-10-12T13:14:41Z"
    },
    {
      "d": "paisd.cl",
      "date": "2025-10-12T13:10:42Z"
    },
    {
      "d": "pinguineitor.cl",
      "date": "2025-10-12T13:08:59Z"
    },
    {
      "d": "biocercos.cl",
      "date": "2025-10-12T13:07:38Z"
    },
    {
      "d": "crochetypunto.cl",
      "date": "2025-10-12T13:00:59Z"
    },
    {
      "d": "marketpc.cl",
      "date": "2025-10-12T13:00:34Z"
    },
    {
      "d": "smartseclc.cl",
      "date": "2025-10-12T12:55:39Z"
    },
    {
      "d": "ceciliagonzalez.cl",
      "date": "2025-10-12T12:54:08Z"
    },
    {
      "d": "levanttech.cl",
      "date": "2025-10-12T12:45:11Z"
    },
    {
      "d": "margaretnarvaez.cl",
      "date": "2025-10-12T12:38:47Z"
    },
    {
      "d": "portalhidrico.cl",
      "date": "2025-10-12T12:31:22Z"
    },
    {
      "d": "hogarseguropro.cl",
      "date": "2025-10-12T12:26:14Z"
    },
    {
      "d": "reforce.cl",
      "date": "2025-10-12T12:20:49Z"
    },
    {
      "d": "lbcorredora.cl",
      "date": "2025-10-12T12:19:51Z"
    },
    {
      "d": "lbseguros.cl",
      "date": "2025-10-12T12:19:49Z"
    },
    {
      "d": "ingeenergy.cl",
      "date": "2025-10-12T12:17:43Z"
    },
    {
      "d": "cuentamix.cl",
      "date": "2025-10-12T12:16:19Z"
    },
    {
      "d": "constructoraogalde.cl",
      "date": "2025-10-12T12:11:29Z"
    },
    {
      "d": "centroderetirogalilea.cl",
      "date": "2025-10-12T12:10:59Z"
    },
    {
      "d": "datastrategy.cl",
      "date": "2025-10-12T12:10:36Z"
    },
    {
      "d": "vigosur.cl",
      "date": "2025-10-12T12:02:32Z"
    },
    {
      "d": "newkar.cl",
      "date": "2025-10-12T11:51:54Z"
    },
    {
      "d": "glifosports.cl",
      "date": "2025-10-12T11:36:41Z"
    },
    {
      "d": "wgmtecnology.cl",
      "date": "2025-10-12T11:34:10Z"
    },
    {
      "d": "rankingpadel.cl",
      "date": "2025-10-12T11:34:09Z"
    },
    {
      "d": "afinidad.cl",
      "date": "2025-10-12T11:32:20Z"
    },
    {
      "d": "busesraver.cl",
      "date": "2025-10-12T11:30:48Z"
    },
    {
      "d": "bigbrother.cl",
      "date": "2025-10-12T11:26:26Z"
    },
    {
      "d": "phefer.cl",
      "date": "2025-10-12T11:24:46Z"
    },
    {
      "d": "hostalvistasol.cl",
      "date": "2025-10-12T11:23:22Z"
    },
    {
      "d": "flipbook.cl",
      "date": "2025-10-12T10:59:25Z"
    },
    {
      "d": "fyno.cl",
      "date": "2025-10-12T10:45:56Z"
    },
    {
      "d": "evmlegal.cl",
      "date": "2025-10-12T10:44:45Z"
    },
    {
      "d": "telasmacarena.cl",
      "date": "2025-10-12T10:42:53Z"
    },
    {
      "d": "clubesdechile.cl",
      "date": "2025-10-12T10:27:55Z"
    },
    {
      "d": "citycraft.cl",
      "date": "2025-10-12T10:26:33Z"
    },
    {
      "d": "osteoprint.cl",
      "date": "2025-10-12T10:23:48Z"
    },
    {
      "d": "elrepresentante.cl",
      "date": "2025-10-12T10:21:20Z"
    },
    {
      "d": "delamarca.cl",
      "date": "2025-10-12T10:21:19Z"
    },
    {
      "d": "axiomaq.cl",
      "date": "2025-10-12T10:18:59Z"
    },
    {
      "d": "euzkera.cl",
      "date": "2025-10-12T10:07:39Z"
    },
    {
      "d": "chickenlovers.cl",
      "date": "2025-10-12T10:04:36Z"
    },
    {
      "d": "natureabeauty.cl",
      "date": "2025-10-12T09:55:20Z"
    },
    {
      "d": "transporteslkw.cl",
      "date": "2025-10-12T09:54:01Z"
    },
    {
      "d": "tinkidoo.cl",
      "date": "2025-10-12T09:51:49Z"
    },
    {
      "d": "mueblesmaquinasyletras.cl",
      "date": "2025-10-12T09:48:07Z"
    },
    {
      "d": "okeywifi.cl",
      "date": "2025-10-12T09:26:40Z"
    },
    {
      "d": "psicologiadeportiva.cl",
      "date": "2025-10-12T09:07:00Z"
    },
    {
      "d": "lyratech.cl",
      "date": "2025-10-12T08:32:37Z"
    },
    {
      "d": "limpizen.cl",
      "date": "2025-10-12T08:27:05Z"
    },
    {
      "d": "pablomad.cl",
      "date": "2025-10-12T08:23:27Z"
    },
    {
      "d": "postulabien.cl",
      "date": "2025-10-12T08:06:17Z"
    },
    {
      "d": "propiedadesurbanas.cl",
      "date": "2025-10-12T07:05:42Z"
    },
    {
      "d": "propiedadescomerciales.cl",
      "date": "2025-10-12T07:05:19Z"
    },
    {
      "d": "videoportero.cl",
      "date": "2025-10-12T06:55:49Z"
    },
    {
      "d": "utilidades.cl",
      "date": "2025-10-12T06:55:26Z"
    },
    {
      "d": "lasuperior.cl",
      "date": "2025-10-12T06:52:51Z"
    },
    {
      "d": "lacuponera.cl",
      "date": "2025-10-12T06:52:20Z"
    },
    {
      "d": "espacioagricola.cl",
      "date": "2025-10-12T06:50:36Z"
    },
    {
      "d": "educaciongratis.cl",
      "date": "2025-10-12T06:50:13Z"
    },
    {
      "d": "comprapro.cl",
      "date": "2025-10-12T06:49:32Z"
    },
    {
      "d": "autentifica.cl",
      "date": "2025-10-12T06:47:37Z"
    },
    {
      "d": "bohemea.cl",
      "date": "2025-10-12T06:45:58Z"
    },
    {
      "d": "vuelo.cl",
      "date": "2025-10-12T06:45:58Z"
    },
    {
      "d": "mentalhealth.cl",
      "date": "2025-10-12T06:44:20Z"
    },
    {
      "d": "impulsia.cl",
      "date": "2025-10-12T04:50:03Z"
    },
    {
      "d": "stockify.cl",
      "date": "2025-10-12T04:17:49Z"
    },
    {
      "d": "efenz.cl",
      "date": "2025-10-12T04:13:23Z"
    },
    {
      "d": "valpobienaldeartepublico.cl",
      "date": "2025-10-12T04:02:23Z"
    },
    {
      "d": "motosyclasicos.cl",
      "date": "2025-10-12T03:56:15Z"
    },
    {
      "d": "artecnologia.cl",
      "date": "2025-10-12T03:53:26Z"
    },
    {
      "d": "vytconstrucciones.cl",
      "date": "2025-10-12T03:07:10Z"
    },
    {
      "d": "monttstoree.cl",
      "date": "2025-10-12T02:33:33Z"
    },
    {
      "d": "pair.cl",
      "date": "2025-10-12T02:08:33Z"
    },
    {
      "d": "esteticacurico.cl",
      "date": "2025-10-12T01:40:38Z"
    },
    {
      "d": "herbalifdistribuidor.cl",
      "date": "2025-10-12T01:09:15Z"
    },
    {
      "d": "vidrieriacristian.cl",
      "date": "2025-10-12T01:00:46Z"
    },
    {
      "d": "aflorar.cl",
      "date": "2025-10-12T00:56:04Z"
    },
    {
      "d": "agilfrut.cl",
      "date": "2025-10-12T00:47:14Z"
    },
    {
      "d": "simbiosislabai.cl",
      "date": "2025-10-12T00:46:08Z"
    },
    {
      "d": "tallerwsp.cl",
      "date": "2025-10-12T00:43:40Z"
    },
    {
      "d": "notablanca.cl",
      "date": "2025-10-12T00:37:39Z"
    },
    {
      "d": "nu-b.cl",
      "date": "2025-10-12T00:35:01Z"
    },
    {
      "d": "tiendacadiz.cl",
      "date": "2025-10-12T00:20:51Z"
    },
    {
      "d": "nexasystems.cl",
      "date": "2025-10-12T00:20:41Z"
    },
    {
      "d": "davidperalta.cl",
      "date": "2025-10-12T00:15:23Z"
    },
    {
      "d": "igorjeria.cl",
      "date": "2025-10-12T00:08:48Z"
    },
    {
      "d": "roastmycode.cl",
      "date": "2025-10-12T00:01:39Z"
    },
    {
      "d": "adaptogenmas.cl",
      "date": "2025-10-11T23:58:25Z"
    },
    {
      "d": "niple.cl",
      "date": "2025-10-11T23:57:46Z"
    },
    {
      "d": "herbalifedistribuidorchile.cl",
      "date": "2025-10-11T23:54:34Z"
    },
    {
      "d": "gestoriahipotecariapropiedades.cl",
      "date": "2025-10-11T23:48:48Z"
    },
    {
      "d": "matildex.cl",
      "date": "2025-10-11T23:47:51Z"
    },
    {
      "d": "aees.cl",
      "date": "2025-10-11T23:42:55Z"
    },
    {
      "d": "renabach.cl",
      "date": "2025-10-11T23:31:52Z"
    },
    {
      "d": "psicologaintegral.cl",
      "date": "2025-10-11T23:30:29Z"
    },
    {
      "d": "elrinconpropiedades.cl",
      "date": "2025-10-11T23:28:30Z"
    },
    {
      "d": "saboryarte.cl",
      "date": "2025-10-11T23:28:23Z"
    },
    {
      "d": "valdiviaciudad.cl",
      "date": "2025-10-11T23:20:24Z"
    },
    {
      "d": "taxonomiadeunidad.cl",
      "date": "2025-10-11T23:16:04Z"
    },
    {
      "d": "aukanleather.cl",
      "date": "2025-10-11T23:11:22Z"
    },
    {
      "d": "aukancuero.cl",
      "date": "2025-10-11T23:11:21Z"
    },
    {
      "d": "constructorashelby.cl",
      "date": "2025-10-11T23:07:13Z"
    },
    {
      "d": "krafte.cl",
      "date": "2025-10-11T23:05:56Z"
    },
    {
      "d": "conectaempresas.cl",
      "date": "2025-10-11T23:02:37Z"
    },
    {
      "d": "arumyxtech.cl",
      "date": "2025-10-11T23:00:26Z"
    },
    {
      "d": "confeccionescorina.cl",
      "date": "2025-10-11T22:58:29Z"
    },
    {
      "d": "ecofrionorte.cl",
      "date": "2025-10-11T22:56:54Z"
    },
    {
      "d": "gerentedefinanzas.cl",
      "date": "2025-10-11T22:53:13Z"
    },
    {
      "d": "ecofrionortewk.cl",
      "date": "2025-10-11T22:50:48Z"
    },
    {
      "d": "aistana.cl",
      "date": "2025-10-11T22:44:12Z"
    },
    {
      "d": "sushivorodelivery.cl",
      "date": "2025-10-11T22:42:18Z"
    },
    {
      "d": "focusvision.cl",
      "date": "2025-10-11T22:37:52Z"
    },
    {
      "d": "unaburger.cl",
      "date": "2025-10-11T22:36:11Z"
    },
    {
      "d": "zei.cl",
      "date": "2025-10-11T22:34:54Z"
    },
    {
      "d": "padillaabogados.cl",
      "date": "2025-10-11T22:32:44Z"
    },
    {
      "d": "buddhasfeet.cl",
      "date": "2025-10-11T22:31:40Z"
    },
    {
      "d": "kreativas.cl",
      "date": "2025-10-11T22:26:58Z"
    },
    {
      "d": "startoyschile.cl",
      "date": "2025-10-11T22:22:57Z"
    },
    {
      "d": "tecno-creative.cl",
      "date": "2025-10-11T22:19:39Z"
    },
    {
      "d": "homedi.cl",
      "date": "2025-10-11T22:19:29Z"
    },
    {
      "d": "fanadeti.cl",
      "date": "2025-10-11T22:17:20Z"
    },
    {
      "d": "datavolve.cl",
      "date": "2025-10-11T22:14:12Z"
    },
    {
      "d": "tiendadelmundo.cl",
      "date": "2025-10-11T22:11:21Z"
    },
    {
      "d": "miasolutions.cl",
      "date": "2025-10-11T22:10:24Z"
    }
  ]
}