{
  "updated": "2025-06-28T11:12:02.397Z",
  "domains": [
    {
      "d": "nubemark.cl",
      "date": "2025-06-28T06:42:29Z"
    },
    {
      "d": "lesbicos.cl",
      "date": "2025-06-28T05:50:56Z"
    },
    {
      "d": "balrodsoluciones.cl",
      "date": "2025-06-28T05:46:26Z"
    },
    {
      "d": "balrod.cl",
      "date": "2025-06-28T05:46:25Z"
    },
    {
      "d": "puntoge.cl",
      "date": "2025-06-28T05:40:16Z"
    },
    {
      "d": "eyaculacionfemenina.cl",
      "date": "2025-06-28T05:35:41Z"
    },
    {
      "d": "squirting.cl",
      "date": "2025-06-28T05:10:30Z"
    },
    {
      "d": "squirt.cl",
      "date": "2025-06-28T05:10:29Z"
    },
    {
      "d": "vetnexa.cl",
      "date": "2025-06-28T04:28:06Z"
    },
    {
      "d": "cerroconcepcion.cl",
      "date": "2025-06-28T03:47:34Z"
    },
    {
      "d": "esvelta.cl",
      "date": "2025-06-28T03:41:20Z"
    },
    {
      "d": "stampo.cl",
      "date": "2025-06-28T03:28:46Z"
    },
    {
      "d": "distritomusic.cl",
      "date": "2025-06-28T02:11:15Z"
    },
    {
      "d": "barbymistica.cl",
      "date": "2025-06-28T02:05:58Z"
    },
    {
      "d": "desp.cl",
      "date": "2025-06-28T01:59:14Z"
    },
    {
      "d": "biofolium.cl",
      "date": "2025-06-28T01:41:46Z"
    },
    {
      "d": "outline.cl",
      "date": "2025-06-28T01:33:29Z"
    },
    {
      "d": "rifaloshermanos.cl",
      "date": "2025-06-28T01:31:02Z"
    },
    {
      "d": "velocitransport.cl",
      "date": "2025-06-28T01:21:10Z"
    },
    {
      "d": "siracusa.cl",
      "date": "2025-06-28T01:05:27Z"
    },
    {
      "d": "reddegratitud.cl",
      "date": "2025-06-28T01:05:01Z"
    },
    {
      "d": "syracuse.cl",
      "date": "2025-06-28T01:01:28Z"
    },
    {
      "d": "desarrollowebpanda.cl",
      "date": "2025-06-28T01:00:33Z"
    },
    {
      "d": "homefy.cl",
      "date": "2025-06-28T00:26:00Z"
    },
    {
      "d": "destaperapido.cl",
      "date": "2025-06-28T00:08:14Z"
    },
    {
      "d": "soolu.cl",
      "date": "2025-06-28T00:02:56Z"
    },
    {
      "d": "civitasplus.cl",
      "date": "2025-06-28T00:01:24Z"
    },
    {
      "d": "lanovedad.cl",
      "date": "2025-06-28T00:01:24Z"
    },
    {
      "d": "qyf.cl",
      "date": "2025-06-27T23:56:24Z"
    },
    {
      "d": "b2ligth.cl",
      "date": "2025-06-27T23:40:41Z"
    },
    {
      "d": "emiliamena.cl",
      "date": "2025-06-27T23:34:41Z"
    },
    {
      "d": "fraudeamplio.cl",
      "date": "2025-06-27T23:29:26Z"
    },
    {
      "d": "mundojoyero.cl",
      "date": "2025-06-27T23:27:37Z"
    },
    {
      "d": "llegomelquiades.cl",
      "date": "2025-06-27T23:21:26Z"
    },
    {
      "d": "velarte.cl",
      "date": "2025-06-27T23:20:58Z"
    },
    {
      "d": "lanuevafm.cl",
      "date": "2025-06-27T23:19:47Z"
    },
    {
      "d": "chascopt.cl",
      "date": "2025-06-27T23:13:57Z"
    },
    {
      "d": "neurofiabilidad.cl",
      "date": "2025-06-27T23:06:59Z"
    },
    {
      "d": "tiemannflammenwall.cl",
      "date": "2025-06-27T23:03:19Z"
    },
    {
      "d": "ia2026.cl",
      "date": "2025-06-27T23:00:40Z"
    },
    {
      "d": "musol.cl",
      "date": "2025-06-27T22:57:11Z"
    },
    {
      "d": "cafeakane.cl",
      "date": "2025-06-27T22:52:45Z"
    },
    {
      "d": "tron-travel.cl",
      "date": "2025-06-27T22:51:26Z"
    },
    {
      "d": "silkair.cl",
      "date": "2025-06-27T22:46:11Z"
    },
    {
      "d": "sg44.cl",
      "date": "2025-06-27T22:44:36Z"
    },
    {
      "d": "sevencaretech.cl",
      "date": "2025-06-27T22:39:28Z"
    },
    {
      "d": "tucontribucionjusta.cl",
      "date": "2025-06-27T22:36:19Z"
    },
    {
      "d": "contribucionesabusivas.cl",
      "date": "2025-06-27T22:34:00Z"
    },
    {
      "d": "congelemostuscontribuciones.cl",
      "date": "2025-06-27T22:30:11Z"
    },
    {
      "d": "congelemoscontribuciones.cl",
      "date": "2025-06-27T22:28:31Z"
    },
    {
      "d": "patitaspelusonas.cl",
      "date": "2025-06-27T22:19:03Z"
    },
    {
      "d": "roperodejuanga.cl",
      "date": "2025-06-27T22:18:29Z"
    },
    {
      "d": "mavimuebles.cl",
      "date": "2025-06-27T22:17:33Z"
    },
    {
      "d": "dentblanche.cl",
      "date": "2025-06-27T22:15:38Z"
    },
    {
      "d": "tiendacasaverde.cl",
      "date": "2025-06-27T22:06:20Z"
    },
    {
      "d": "jociis.cl",
      "date": "2025-06-27T22:05:49Z"
    },
    {
      "d": "tomaturemedio.cl",
      "date": "2025-06-27T21:49:06Z"
    },
    {
      "d": "tumapadelalma.cl",
      "date": "2025-06-27T21:44:50Z"
    },
    {
      "d": "sandmotion.cl",
      "date": "2025-06-27T21:43:38Z"
    },
    {
      "d": "rifazo.cl",
      "date": "2025-06-27T21:37:25Z"
    },
    {
      "d": "vpssecurity.cl",
      "date": "2025-06-27T21:35:39Z"
    },
    {
      "d": "raicesdelsurpropiedades.cl",
      "date": "2025-06-27T21:26:23Z"
    },
    {
      "d": "medicinaviva.cl",
      "date": "2025-06-27T21:26:05Z"
    },
    {
      "d": "martinortega.cl",
      "date": "2025-06-27T21:25:07Z"
    },
    {
      "d": "pandevidaeterna.cl",
      "date": "2025-06-27T21:22:45Z"
    },
    {
      "d": "330.cl",
      "date": "2025-06-27T21:21:59Z"
    },
    {
      "d": "cyberbits.cl",
      "date": "2025-06-27T21:15:20Z"
    },
    {
      "d": "happinetics.cl",
      "date": "2025-06-27T21:06:17Z"
    },
    {
      "d": "iecpa.cl",
      "date": "2025-06-27T21:04:26Z"
    },
    {
      "d": "reservanegra.cl",
      "date": "2025-06-27T21:01:51Z"
    },
    {
      "d": "fuyu.cl",
      "date": "2025-06-27T21:00:40Z"
    },
    {
      "d": "legadoandino.cl",
      "date": "2025-06-27T20:57:36Z"
    },
    {
      "d": "elhipotecario.cl",
      "date": "2025-06-27T20:56:38Z"
    },
    {
      "d": "rinotox.cl",
      "date": "2025-06-27T20:55:14Z"
    },
    {
      "d": "drajimenajalil.cl",
      "date": "2025-06-27T20:55:14Z"
    },
    {
      "d": "evalab.cl",
      "date": "2025-06-27T20:49:20Z"
    },
    {
      "d": "cartadigitalpro.cl",
      "date": "2025-06-27T20:43:30Z"
    },
    {
      "d": "purezalimenta.cl",
      "date": "2025-06-27T20:42:56Z"
    },
    {
      "d": "lavidaenperfumes.cl",
      "date": "2025-06-27T20:41:31Z"
    },
    {
      "d": "fuentek.cl",
      "date": "2025-06-27T20:36:20Z"
    },
    {
      "d": "shopana.cl",
      "date": "2025-06-27T20:31:48Z"
    },
    {
      "d": "myccentrologistico.cl",
      "date": "2025-06-27T20:31:44Z"
    },
    {
      "d": "cotitos.cl",
      "date": "2025-06-27T20:31:02Z"
    },
    {
      "d": "fuegoymasas.cl",
      "date": "2025-06-27T20:23:32Z"
    },
    {
      "d": "cydralink.cl",
      "date": "2025-06-27T20:11:36Z"
    },
    {
      "d": "wylla.cl",
      "date": "2025-06-27T20:07:52Z"
    },
    {
      "d": "seminariolecparaaprender2025.cl",
      "date": "2025-06-27T20:07:19Z"
    },
    {
      "d": "xpandcapacita.cl",
      "date": "2025-06-27T20:07:04Z"
    },
    {
      "d": "mundonaturalyesoterico.cl",
      "date": "2025-06-27T20:03:01Z"
    },
    {
      "d": "plataformaindap.cl",
      "date": "2025-06-27T19:56:19Z"
    },
    {
      "d": "cotizadordeisapre.cl",
      "date": "2025-06-27T19:53:28Z"
    },
    {
      "d": "renacentista.cl",
      "date": "2025-06-27T19:50:38Z"
    },
    {
      "d": "abogadojuanpenailillo.cl",
      "date": "2025-06-27T19:48:21Z"
    },
    {
      "d": "trendenciamkt.cl",
      "date": "2025-06-27T19:45:03Z"
    },
    {
      "d": "multibest.cl",
      "date": "2025-06-27T19:40:09Z"
    },
    {
      "d": "trazoanimal.cl",
      "date": "2025-06-27T19:31:59Z"
    },
    {
      "d": "chicosbuenos.cl",
      "date": "2025-06-27T19:25:41Z"
    },
    {
      "d": "oddcount.cl",
      "date": "2025-06-27T19:20:25Z"
    },
    {
      "d": "roseblack.cl",
      "date": "2025-06-27T19:20:15Z"
    },
    {
      "d": "inscene.cl",
      "date": "2025-06-27T19:17:02Z"
    },
    {
      "d": "mvpetros.cl",
      "date": "2025-06-27T19:16:36Z"
    },
    {
      "d": "estampadosecounder.cl",
      "date": "2025-06-27T19:15:09Z"
    },
    {
      "d": "nadadores.cl",
      "date": "2025-06-27T19:13:49Z"
    },
    {
      "d": "digitalbikemolina.cl",
      "date": "2025-06-27T19:06:12Z"
    },
    {
      "d": "rlab.cl",
      "date": "2025-06-27T19:04:42Z"
    },
    {
      "d": "joyeriadistefano.cl",
      "date": "2025-06-27T19:02:00Z"
    },
    {
      "d": "biosys.cl",
      "date": "2025-06-27T19:01:57Z"
    },
    {
      "d": "eskalar.cl",
      "date": "2025-06-27T19:00:45Z"
    },
    {
      "d": "ordex.cl",
      "date": "2025-06-27T18:55:48Z"
    },
    {
      "d": "aulanoticia.cl",
      "date": "2025-06-27T18:52:31Z"
    },
    {
      "d": "entrenamientopaes.cl",
      "date": "2025-06-27T18:49:57Z"
    },
    {
      "d": "parquelosvolcanes.cl",
      "date": "2025-06-27T18:47:28Z"
    },
    {
      "d": "nidoclass.cl",
      "date": "2025-06-27T18:46:50Z"
    },
    {
      "d": "dmvpdigital.cl",
      "date": "2025-06-27T18:45:43Z"
    },
    {
      "d": "strongbest.cl",
      "date": "2025-06-27T18:40:25Z"
    },
    {
      "d": "agrobest.cl",
      "date": "2025-06-27T18:40:25Z"
    },
    {
      "d": "dulcestudiochile.cl",
      "date": "2025-06-27T18:35:49Z"
    },
    {
      "d": "hotemilodon.cl",
      "date": "2025-06-27T18:32:23Z"
    },
    {
      "d": "saludpuentealtodigital.cl",
      "date": "2025-06-27T18:26:24Z"
    },
    {
      "d": "saludvalparaisodigital.cl",
      "date": "2025-06-27T18:25:25Z"
    },
    {
      "d": "saludtemucodigital.cl",
      "date": "2025-06-27T18:25:19Z"
    },
    {
      "d": "saludosornodigital.cl",
      "date": "2025-06-27T18:25:18Z"
    },
    {
      "d": "saludsantiagodigital.cl",
      "date": "2025-06-27T18:24:59Z"
    },
    {
      "d": "saludmaipudigital.cl",
      "date": "2025-06-27T18:24:52Z"
    },
    {
      "d": "saludtalcahuanodigital.cl",
      "date": "2025-06-27T18:24:42Z"
    },
    {
      "d": "fundacionatelier.cl",
      "date": "2025-06-27T18:20:34Z"
    },
    {
      "d": "mrkpropiedades.cl",
      "date": "2025-06-27T18:19:26Z"
    },
    {
      "d": "aulavirtualmoodle.cl",
      "date": "2025-06-27T18:19:13Z"
    },
    {
      "d": "arrayanesdelcolico.cl",
      "date": "2025-06-27T18:17:25Z"
    },
    {
      "d": "kaiserpresidente.cl",
      "date": "2025-06-27T18:10:35Z"
    },
    {
      "d": "saludlosangelesdigital.cl",
      "date": "2025-06-27T18:08:34Z"
    },
    {
      "d": "saludlafloridadigital.cl",
      "date": "2025-06-27T18:07:59Z"
    },
    {
      "d": "saludantofagastadigital.cl",
      "date": "2025-06-27T18:07:21Z"
    },
    {
      "d": "tecninox.cl",
      "date": "2025-06-27T18:04:43Z"
    },
    {
      "d": "contacto-cotiza.cl",
      "date": "2025-06-27T18:02:55Z"
    },
    {
      "d": "panteon.cl",
      "date": "2025-06-27T18:01:49Z"
    },
    {
      "d": "hanlo.cl",
      "date": "2025-06-27T17:58:08Z"
    },
    {
      "d": "feltbysayen.cl",
      "date": "2025-06-27T17:53:37Z"
    },
    {
      "d": "jonna.cl",
      "date": "2025-06-27T17:52:50Z"
    },
    {
      "d": "petfect.cl",
      "date": "2025-06-27T17:51:26Z"
    },
    {
      "d": "sayenandco.cl",
      "date": "2025-06-27T17:49:55Z"
    },
    {
      "d": "contribucionesjustas.cl",
      "date": "2025-06-27T17:46:04Z"
    },
    {
      "d": "twistmarket.cl",
      "date": "2025-06-27T17:45:11Z"
    },
    {
      "d": "susein.cl",
      "date": "2025-06-27T17:44:56Z"
    },
    {
      "d": "inkstore.cl",
      "date": "2025-06-27T17:42:28Z"
    },
    {
      "d": "nomascontribuciones.cl",
      "date": "2025-06-27T17:41:32Z"
    },
    {
      "d": "usadoconestilo.cl",
      "date": "2025-06-27T17:33:16Z"
    },
    {
      "d": "unomasajes.cl",
      "date": "2025-06-27T17:30:25Z"
    },
    {
      "d": "pooki.cl",
      "date": "2025-06-27T17:30:20Z"
    },
    {
      "d": "cuentasvip.cl",
      "date": "2025-06-27T17:28:18Z"
    },
    {
      "d": "automotoracmt.cl",
      "date": "2025-06-27T17:28:07Z"
    },
    {
      "d": "psicologapatriciasaez.cl",
      "date": "2025-06-27T17:25:51Z"
    },
    {
      "d": "altivus.cl",
      "date": "2025-06-27T17:20:59Z"
    },
    {
      "d": "provinciadigital.cl",
      "date": "2025-06-27T17:15:24Z"
    },
    {
      "d": "lyancomputer.cl",
      "date": "2025-06-27T17:13:38Z"
    },
    {
      "d": "mandalaeventos.cl",
      "date": "2025-06-27T17:08:45Z"
    },
    {
      "d": "asesoriasjimenez.cl",
      "date": "2025-06-27T17:08:29Z"
    },
    {
      "d": "fivraestudio.cl",
      "date": "2025-06-27T17:06:56Z"
    },
    {
      "d": "elregalitotiendaonline.cl",
      "date": "2025-06-27T17:03:06Z"
    },
    {
      "d": "puelolabs.cl",
      "date": "2025-06-27T17:00:54Z"
    },
    {
      "d": "elunhome.cl",
      "date": "2025-06-27T16:57:07Z"
    },
    {
      "d": "opusclass.cl",
      "date": "2025-06-27T16:56:07Z"
    },
    {
      "d": "antisismicos.cl",
      "date": "2025-06-27T16:49:26Z"
    },
    {
      "d": "weldtek.cl",
      "date": "2025-06-27T16:47:01Z"
    },
    {
      "d": "notrocketscience.cl",
      "date": "2025-06-27T16:43:03Z"
    },
    {
      "d": "cozysantiago.cl",
      "date": "2025-06-27T16:42:15Z"
    },
    {
      "d": "tallerarteideas.cl",
      "date": "2025-06-27T16:40:53Z"
    },
    {
      "d": "piwkepatagonia.cl",
      "date": "2025-06-27T16:37:49Z"
    },
    {
      "d": "chileway.cl",
      "date": "2025-06-27T16:34:35Z"
    },
    {
      "d": "soyalin.cl",
      "date": "2025-06-27T16:33:55Z"
    },
    {
      "d": "frmefpchile.cl",
      "date": "2025-06-27T16:33:10Z"
    },
    {
      "d": "almamiel.cl",
      "date": "2025-06-27T16:32:15Z"
    },
    {
      "d": "terapialiteraria.cl",
      "date": "2025-06-27T16:30:39Z"
    },
    {
      "d": "marilenyjavierurzuapropiedades.cl",
      "date": "2025-06-27T16:30:20Z"
    },
    {
      "d": "basemorrena.cl",
      "date": "2025-06-27T16:29:51Z"
    },
    {
      "d": "loynext.cl",
      "date": "2025-06-27T16:28:17Z"
    },
    {
      "d": "biodanzante.cl",
      "date": "2025-06-27T16:25:55Z"
    },
    {
      "d": "richtersic.cl",
      "date": "2025-06-27T16:24:37Z"
    },
    {
      "d": "corvice.cl",
      "date": "2025-06-27T16:22:40Z"
    },
    {
      "d": "mueblesnoko.cl",
      "date": "2025-06-27T16:21:07Z"
    },
    {
      "d": "psignaciovasquez.cl",
      "date": "2025-06-27T16:17:07Z"
    },
    {
      "d": "vivaloclean.cl",
      "date": "2025-06-27T16:17:04Z"
    },
    {
      "d": "esthetichouse.cl",
      "date": "2025-06-27T16:16:31Z"
    },
    {
      "d": "classdent.cl",
      "date": "2025-06-27T16:13:37Z"
    },
    {
      "d": "juv.cl",
      "date": "2025-06-27T16:10:02Z"
    },
    {
      "d": "cmdgalapagos.cl",
      "date": "2025-06-27T16:09:25Z"
    },
    {
      "d": "ecostardyl.cl",
      "date": "2025-06-27T16:09:10Z"
    },
    {
      "d": "vipass.cl",
      "date": "2025-06-27T16:07:38Z"
    },
    {
      "d": "asesorialaboralchile.cl",
      "date": "2025-06-27T16:06:07Z"
    },
    {
      "d": "laconcorde.cl",
      "date": "2025-06-27T16:04:56Z"
    },
    {
      "d": "celec.cl",
      "date": "2025-06-27T16:04:55Z"
    },
    {
      "d": "nlucia.cl",
      "date": "2025-06-27T16:04:44Z"
    },
    {
      "d": "fazusach.cl",
      "date": "2025-06-27T16:03:29Z"
    },
    {
      "d": "ssnutrition.cl",
      "date": "2025-06-27T16:03:06Z"
    },
    {
      "d": "nidolucia.cl",
      "date": "2025-06-27T16:02:10Z"
    },
    {
      "d": "visionary-laparva.cl",
      "date": "2025-06-27T16:00:23Z"
    },
    {
      "d": "haztuaporte.cl",
      "date": "2025-06-27T15:59:48Z"
    },
    {
      "d": "tobashalcones.cl",
      "date": "2025-06-27T15:58:45Z"
    },
    {
      "d": "elbuensurtido.cl",
      "date": "2025-06-27T15:55:32Z"
    },
    {
      "d": "mbrental.cl",
      "date": "2025-06-27T15:54:50Z"
    },
    {
      "d": "qhali.cl",
      "date": "2025-06-27T15:53:12Z"
    },
    {
      "d": "brone.cl",
      "date": "2025-06-27T15:52:59Z"
    },
    {
      "d": "inzpirafragrances.cl",
      "date": "2025-06-27T15:50:53Z"
    },
    {
      "d": "radioimpactofm.cl",
      "date": "2025-06-27T15:50:24Z"
    },
    {
      "d": "magicmind.cl",
      "date": "2025-06-27T15:50:15Z"
    },
    {
      "d": "sanamama.cl",
      "date": "2025-06-27T15:48:39Z"
    },
    {
      "d": "qraudio.cl",
      "date": "2025-06-27T15:45:36Z"
    },
    {
      "d": "endulzameldia.cl",
      "date": "2025-06-27T15:40:51Z"
    },
    {
      "d": "inverplas.cl",
      "date": "2025-06-27T15:30:48Z"
    },
    {
      "d": "sublitech.cl",
      "date": "2025-06-27T15:30:03Z"
    },
    {
      "d": "fauza.cl",
      "date": "2025-06-27T15:27:47Z"
    },
    {
      "d": "enviodirectochilepro.cl",
      "date": "2025-06-27T15:25:48Z"
    },
    {
      "d": "dialogue.cl",
      "date": "2025-06-27T15:24:32Z"
    },
    {
      "d": "jauria.cl",
      "date": "2025-06-27T15:24:25Z"
    },
    {
      "d": "amedicalpro.cl",
      "date": "2025-06-27T15:23:53Z"
    },
    {
      "d": "ecoagenda.cl",
      "date": "2025-06-27T15:21:16Z"
    },
    {
      "d": "arpainversiones.cl",
      "date": "2025-06-27T15:17:38Z"
    },
    {
      "d": "amezingstudio.cl",
      "date": "2025-06-27T15:12:44Z"
    },
    {
      "d": "clinicakindermed.cl",
      "date": "2025-06-27T15:11:58Z"
    },
    {
      "d": "vinifan.cl",
      "date": "2025-06-27T15:10:18Z"
    },
    {
      "d": "corteplac.cl",
      "date": "2025-06-27T15:04:42Z"
    },
    {
      "d": "centroequitas.cl",
      "date": "2025-06-27T15:02:32Z"
    },
    {
      "d": "fencecovers.cl",
      "date": "2025-06-27T15:02:08Z"
    },
    {
      "d": "tusugardaddy.cl",
      "date": "2025-06-27T14:58:56Z"
    },
    {
      "d": "danidev.cl",
      "date": "2025-06-27T14:55:35Z"
    },
    {
      "d": "lunica.cl",
      "date": "2025-06-27T14:54:31Z"
    },
    {
      "d": "aguabellavita.cl",
      "date": "2025-06-27T14:50:11Z"
    },
    {
      "d": "smartmeter.cl",
      "date": "2025-06-27T14:45:40Z"
    },
    {
      "d": "importadorabhspa.cl",
      "date": "2025-06-27T14:42:57Z"
    },
    {
      "d": "corposalud.cl",
      "date": "2025-06-27T14:42:41Z"
    },
    {
      "d": "smartcab.cl",
      "date": "2025-06-27T14:42:01Z"
    },
    {
      "d": "avanceenpesos.cl",
      "date": "2025-06-27T14:41:04Z"
    },
    {
      "d": "costcochile.cl",
      "date": "2025-06-27T14:37:48Z"
    },
    {
      "d": "kirklandwater.cl",
      "date": "2025-06-27T14:35:43Z"
    },
    {
      "d": "elui.cl",
      "date": "2025-06-27T14:35:37Z"
    },
    {
      "d": "pistachos-sagredo.cl",
      "date": "2025-06-27T14:33:59Z"
    },
    {
      "d": "kirklandchile.cl",
      "date": "2025-06-27T14:32:57Z"
    },
    {
      "d": "wweb.cl",
      "date": "2025-06-27T14:29:45Z"
    },
    {
      "d": "delamanta.cl",
      "date": "2025-06-27T14:27:25Z"
    },
    {
      "d": "curvella.cl",
      "date": "2025-06-27T14:25:56Z"
    },
    {
      "d": "portalsomosalmacenes.cl",
      "date": "2025-06-27T14:25:03Z"
    },
    {
      "d": "sublidatha.cl",
      "date": "2025-06-27T14:24:26Z"
    },
    {
      "d": "vivelitueche.cl",
      "date": "2025-06-27T14:22:14Z"
    },
    {
      "d": "thenorthfaceendurancetrail.cl",
      "date": "2025-06-27T14:21:41Z"
    },
    {
      "d": "clinicaeden.cl",
      "date": "2025-06-27T14:21:03Z"
    },
    {
      "d": "noischile.cl",
      "date": "2025-06-27T14:17:02Z"
    },
    {
      "d": "alcarspa.cl",
      "date": "2025-06-27T14:11:39Z"
    },
    {
      "d": "delstretto.cl",
      "date": "2025-06-27T14:08:28Z"
    },
    {
      "d": "vicmicreaciones.cl",
      "date": "2025-06-27T14:08:23Z"
    },
    {
      "d": "365business.cl",
      "date": "2025-06-27T14:06:59Z"
    },
    {
      "d": "archicorporativo.cl",
      "date": "2025-06-27T14:05:03Z"
    },
    {
      "d": "mcseguros.cl",
      "date": "2025-06-27T14:05:02Z"
    },
    {
      "d": "novateksur.cl",
      "date": "2025-06-27T14:01:14Z"
    },
    {
      "d": "cockeringles.cl",
      "date": "2025-06-27T13:59:37Z"
    },
    {
      "d": "collabos.cl",
      "date": "2025-06-27T13:59:31Z"
    },
    {
      "d": "bestcontanerhouses.cl",
      "date": "2025-06-27T13:56:08Z"
    },
    {
      "d": "provinciaabogados.cl",
      "date": "2025-06-27T13:53:55Z"
    },
    {
      "d": "raleos.cl",
      "date": "2025-06-27T13:46:29Z"
    },
    {
      "d": "pibpa.cl",
      "date": "2025-06-27T13:41:30Z"
    },
    {
      "d": "psicologiapp.cl",
      "date": "2025-06-27T13:41:07Z"
    },
    {
      "d": "invix.cl",
      "date": "2025-06-27T13:38:38Z"
    },
    {
      "d": "olnarauco.cl",
      "date": "2025-06-27T13:33:13Z"
    },
    {
      "d": "alemanpenquista.cl",
      "date": "2025-06-27T13:31:52Z"
    },
    {
      "d": "surturtv.cl",
      "date": "2025-06-27T13:30:18Z"
    },
    {
      "d": "mcrclinicaestetica.cl",
      "date": "2025-06-27T13:28:38Z"
    },
    {
      "d": "munayterapiasholisticas.cl",
      "date": "2025-06-27T13:27:11Z"
    },
    {
      "d": "marketingaustral.cl",
      "date": "2025-06-27T13:23:37Z"
    },
    {
      "d": "lashe.cl",
      "date": "2025-06-27T13:21:21Z"
    },
    {
      "d": "consultoriojudicial.cl",
      "date": "2025-06-27T13:19:39Z"
    },
    {
      "d": "proteccionlaboralconcepcion.cl",
      "date": "2025-06-27T13:19:36Z"
    },
    {
      "d": "francorrea.cl",
      "date": "2025-06-27T13:19:27Z"
    },
    {
      "d": "drafrancorrea.cl",
      "date": "2025-06-27T13:19:26Z"
    },
    {
      "d": "doctorafrancorrea.cl",
      "date": "2025-06-27T13:19:25Z"
    },
    {
      "d": "ati-fondoconcursable.cl",
      "date": "2025-06-27T13:19:00Z"
    },
    {
      "d": "surstation.cl",
      "date": "2025-06-27T13:18:58Z"
    },
    {
      "d": "innovisionsecurity.cl",
      "date": "2025-06-27T13:18:24Z"
    },
    {
      "d": "donmatiasinmobiliaria.cl",
      "date": "2025-06-27T13:16:46Z"
    },
    {
      "d": "dentbird.cl",
      "date": "2025-06-27T13:16:05Z"
    },
    {
      "d": "mauricioleyton.cl",
      "date": "2025-06-27T13:15:49Z"
    },
    {
      "d": "miarepazo.cl",
      "date": "2025-06-27T13:14:39Z"
    },
    {
      "d": "granosymiel.cl",
      "date": "2025-06-27T13:14:11Z"
    },
    {
      "d": "wellnatics.cl",
      "date": "2025-06-27T13:14:02Z"
    },
    {
      "d": "smilebot.cl",
      "date": "2025-06-27T13:12:04Z"
    },
    {
      "d": "hotclick.cl",
      "date": "2025-06-27T13:06:06Z"
    },
    {
      "d": "carretemovil.cl",
      "date": "2025-06-27T13:05:35Z"
    },
    {
      "d": "marquezpetfood.cl",
      "date": "2025-06-27T13:04:47Z"
    },
    {
      "d": "powermedia.cl",
      "date": "2025-06-27T13:04:35Z"
    },
    {
      "d": "starkplas.cl",
      "date": "2025-06-27T13:03:18Z"
    },
    {
      "d": "bozmann.cl",
      "date": "2025-06-27T13:03:17Z"
    },
    {
      "d": "esejota.cl",
      "date": "2025-06-27T12:59:57Z"
    },
    {
      "d": "talentix.cl",
      "date": "2025-06-27T12:57:49Z"
    },
    {
      "d": "draclaudiamoreno.cl",
      "date": "2025-06-27T12:57:31Z"
    },
    {
      "d": "elijomiplan.cl",
      "date": "2025-06-27T12:52:15Z"
    },
    {
      "d": "redbridge.cl",
      "date": "2025-06-27T12:45:18Z"
    },
    {
      "d": "mujo.cl",
      "date": "2025-06-27T12:44:05Z"
    },
    {
      "d": "okweb.cl",
      "date": "2025-06-27T12:42:27Z"
    },
    {
      "d": "planetazul.cl",
      "date": "2025-06-27T12:41:26Z"
    },
    {
      "d": "americanfit.cl",
      "date": "2025-06-27T12:41:11Z"
    },
    {
      "d": "instalados.cl",
      "date": "2025-06-27T12:41:00Z"
    },
    {
      "d": "tattooblack.cl",
      "date": "2025-06-27T12:38:40Z"
    },
    {
      "d": "mejillonesdelsur.cl",
      "date": "2025-06-27T12:38:15Z"
    },
    {
      "d": "leadher.cl",
      "date": "2025-06-27T12:36:47Z"
    },
    {
      "d": "alfa-zeta.cl",
      "date": "2025-06-27T12:35:03Z"
    },
    {
      "d": "transportespergo.cl",
      "date": "2025-06-27T12:33:59Z"
    },
    {
      "d": "chileartepublico.cl",
      "date": "2025-06-27T12:32:45Z"
    },
    {
      "d": "afdemlautaro.cl",
      "date": "2025-06-27T12:32:33Z"
    },
    {
      "d": "fundacionkuzaw.cl",
      "date": "2025-06-27T12:32:24Z"
    },
    {
      "d": "equipamed.cl",
      "date": "2025-06-27T12:29:24Z"
    },
    {
      "d": "cycabogado.cl",
      "date": "2025-06-27T12:21:42Z"
    },
    {
      "d": "servielec.cl",
      "date": "2025-06-27T12:21:08Z"
    },
    {
      "d": "maestranzamg.cl",
      "date": "2025-06-27T12:17:27Z"
    },
    {
      "d": "e4s.cl",
      "date": "2025-06-27T12:16:28Z"
    },
    {
      "d": "codigo8.cl",
      "date": "2025-06-27T12:10:52Z"
    },
    {
      "d": "vccargo.cl",
      "date": "2025-06-27T12:08:06Z"
    },
    {
      "d": "nuevapiel.cl",
      "date": "2025-06-27T12:07:46Z"
    },
    {
      "d": "maxifer.cl",
      "date": "2025-06-27T12:07:34Z"
    },
    {
      "d": "verbify.cl",
      "date": "2025-06-27T12:06:35Z"
    },
    {
      "d": "mallerym.cl",
      "date": "2025-06-27T12:05:53Z"
    },
    {
      "d": "artemondtaller.cl",
      "date": "2025-06-27T12:05:47Z"
    },
    {
      "d": "revistavitacura.cl",
      "date": "2025-06-27T12:04:27Z"
    },
    {
      "d": "revistalascondes.cl",
      "date": "2025-06-27T12:04:26Z"
    },
    {
      "d": "repuestosvimat.cl",
      "date": "2025-06-27T12:03:28Z"
    },
    {
      "d": "webapps.cl",
      "date": "2025-06-27T12:01:49Z"
    },
    {
      "d": "energiacuantica.cl",
      "date": "2025-06-27T12:01:33Z"
    },
    {
      "d": "centpi.cl",
      "date": "2025-06-27T12:00:35Z"
    },
    {
      "d": "blueimport.cl",
      "date": "2025-06-27T11:55:55Z"
    },
    {
      "d": "fm2gi.cl",
      "date": "2025-06-27T11:55:34Z"
    },
    {
      "d": "tiendacasasdelbosque.cl",
      "date": "2025-06-27T11:55:05Z"
    },
    {
      "d": "caletahornos.cl",
      "date": "2025-06-27T11:50:56Z"
    },
    {
      "d": "numerae.cl",
      "date": "2025-06-27T11:50:39Z"
    },
    {
      "d": "radarfinanciero.cl",
      "date": "2025-06-27T11:50:38Z"
    },
    {
      "d": "rallycoffe.cl",
      "date": "2025-06-27T11:49:06Z"
    },
    {
      "d": "mueblebueno.cl",
      "date": "2025-06-27T11:46:56Z"
    },
    {
      "d": "dcconsulting.cl",
      "date": "2025-06-27T11:46:51Z"
    },
    {
      "d": "jrmpropiedades.cl",
      "date": "2025-06-27T11:46:25Z"
    },
    {
      "d": "cromalab.cl",
      "date": "2025-06-27T11:45:28Z"
    },
    {
      "d": "mundocongelados.cl",
      "date": "2025-06-27T11:45:09Z"
    },
    {
      "d": "alfafugas.cl",
      "date": "2025-06-27T11:42:45Z"
    },
    {
      "d": "coompas.cl",
      "date": "2025-06-27T11:39:56Z"
    },
    {
      "d": "bogajo.cl",
      "date": "2025-06-27T11:39:54Z"
    },
    {
      "d": "fullmart.cl",
      "date": "2025-06-27T11:38:53Z"
    },
    {
      "d": "inviertehoy.cl",
      "date": "2025-06-27T11:38:53Z"
    },
    {
      "d": "mtchile.cl",
      "date": "2025-06-27T11:33:14Z"
    },
    {
      "d": "petitwines.cl",
      "date": "2025-06-27T11:30:42Z"
    },
    {
      "d": "joyasyestilos.cl",
      "date": "2025-06-27T11:26:44Z"
    },
    {
      "d": "recoverpoint.cl",
      "date": "2025-06-27T11:25:38Z"
    },
    {
      "d": "idmrental.cl",
      "date": "2025-06-27T11:24:52Z"
    },
    {
      "d": "centurygraficas.cl",
      "date": "2025-06-27T11:23:11Z"
    },
    {
      "d": "firevision.cl",
      "date": "2025-06-27T11:21:51Z"
    },
    {
      "d": "termicasur.cl",
      "date": "2025-06-27T11:21:35Z"
    },
    {
      "d": "arquitecturaterrazo.cl",
      "date": "2025-06-27T11:21:34Z"
    },
    {
      "d": "centuryfest.cl",
      "date": "2025-06-27T11:21:16Z"
    },
    {
      "d": "metricapublica.cl",
      "date": "2025-06-27T11:20:55Z"
    },
    {
      "d": "guerreroszprime.cl",
      "date": "2025-06-27T11:20:38Z"
    },
    {
      "d": "espaciodual.cl",
      "date": "2025-06-27T11:20:05Z"
    },
    {
      "d": "sanandresdelvalle.cl",
      "date": "2025-06-27T11:18:31Z"
    },
    {
      "d": "centuryfestchile.cl",
      "date": "2025-06-27T11:16:42Z"
    },
    {
      "d": "holasoyisidora.cl",
      "date": "2025-06-27T11:15:47Z"
    },
    {
      "d": "imelia.cl",
      "date": "2025-06-27T11:14:31Z"
    },
    {
      "d": "exentra.cl",
      "date": "2025-06-27T11:13:55Z"
    },
    {
      "d": "norteabanicos.cl",
      "date": "2025-06-27T11:13:41Z"
    },
    {
      "d": "abaniko.cl",
      "date": "2025-06-27T11:12:18Z"
    },
    {
      "d": "rmsvc-marinalascondes.cl",
      "date": "2025-06-27T11:10:08Z"
    },
    {
      "d": "eroslibreriaeimpresiones.cl",
      "date": "2025-06-27T11:08:47Z"
    },
    {
      "d": "bjz.cl",
      "date": "2025-06-27T11:07:39Z"
    },
    {
      "d": "utermevn.cl",
      "date": "2025-06-27T11:04:33Z"
    },
    {
      "d": "recuperacionciudadana.cl",
      "date": "2025-06-27T11:03:28Z"
    },
    {
      "d": "idnrental.cl",
      "date": "2025-06-27T11:03:01Z"
    },
    {
      "d": "homebattery.cl",
      "date": "2025-06-27T11:00:57Z"
    },
    {
      "d": "1redbet.cl",
      "date": "2025-06-27T11:00:56Z"
    },
    {
      "d": "1redbet-chile.cl",
      "date": "2025-06-27T11:00:55Z"
    },
    {
      "d": "1redbet-casino.cl",
      "date": "2025-06-27T11:00:54Z"
    },
    {
      "d": "mejorisaprechile.cl",
      "date": "2025-06-27T11:00:00Z"
    },
    {
      "d": "metfluid.cl",
      "date": "2025-06-27T10:58:46Z"
    },
    {
      "d": "slubangt.cl",
      "date": "2025-06-27T10:58:04Z"
    },
    {
      "d": "pippaschic.cl",
      "date": "2025-06-27T10:56:38Z"
    },
    {
      "d": "tabula-firevision.cl",
      "date": "2025-06-27T10:56:16Z"
    },
    {
      "d": "blackmambas.cl",
      "date": "2025-06-27T10:54:34Z"
    },
    {
      "d": "caromora.cl",
      "date": "2025-06-27T10:53:53Z"
    },
    {
      "d": "perimetrik.cl",
      "date": "2025-06-27T10:53:17Z"
    },
    {
      "d": "smartpoint.cl",
      "date": "2025-06-27T10:51:56Z"
    },
    {
      "d": "cicbq.cl",
      "date": "2025-06-27T10:50:15Z"
    },
    {
      "d": "abastecchile.cl",
      "date": "2025-06-27T10:47:16Z"
    },
    {
      "d": "katzservice.cl",
      "date": "2025-06-27T10:46:39Z"
    },
    {
      "d": "terralka.cl",
      "date": "2025-06-27T10:46:15Z"
    },
    {
      "d": "chicboutique.cl",
      "date": "2025-06-27T10:45:36Z"
    },
    {
      "d": "campingrutanomade.cl",
      "date": "2025-06-27T10:44:26Z"
    },
    {
      "d": "adaptacionprofunda.cl",
      "date": "2025-06-27T10:44:26Z"
    },
    {
      "d": "icmetrica.cl",
      "date": "2025-06-27T10:41:07Z"
    },
    {
      "d": "vectorialgroup.cl",
      "date": "2025-06-27T10:38:03Z"
    },
    {
      "d": "vulkanecapacitaciones.cl",
      "date": "2025-06-27T10:36:41Z"
    },
    {
      "d": "kolmin.cl",
      "date": "2025-06-27T10:35:11Z"
    },
    {
      "d": "puelcheenergy.cl",
      "date": "2025-06-27T10:34:19Z"
    },
    {
      "d": "bhadra.cl",
      "date": "2025-06-27T10:32:58Z"
    },
    {
      "d": "cvetcahuil.cl",
      "date": "2025-06-27T10:32:04Z"
    },
    {
      "d": "confirmalo.cl",
      "date": "2025-06-27T10:29:27Z"
    },
    {
      "d": "namichile.cl",
      "date": "2025-06-27T10:27:04Z"
    },
    {
      "d": "renovaustral.cl",
      "date": "2025-06-27T10:25:28Z"
    },
    {
      "d": "kicar.cl",
      "date": "2025-06-27T10:20:55Z"
    },
    {
      "d": "blackwolf.cl",
      "date": "2025-06-27T10:18:42Z"
    },
    {
      "d": "m2pym.cl",
      "date": "2025-06-27T10:17:00Z"
    },
    {
      "d": "chupitonic.cl",
      "date": "2025-06-27T10:10:57Z"
    },
    {
      "d": "oxisports.cl",
      "date": "2025-06-27T10:09:58Z"
    },
    {
      "d": "uraqidesign.cl",
      "date": "2025-06-27T10:09:19Z"
    },
    {
      "d": "bodysportgym.cl",
      "date": "2025-06-27T10:07:19Z"
    },
    {
      "d": "masointegra.cl",
      "date": "2025-06-27T10:06:06Z"
    },
    {
      "d": "ignaciomallea.cl",
      "date": "2025-06-27T10:05:48Z"
    },
    {
      "d": "efectivoya.cl",
      "date": "2025-06-27T10:01:31Z"
    },
    {
      "d": "epowert.cl",
      "date": "2025-06-27T09:57:14Z"
    },
    {
      "d": "unicash.cl",
      "date": "2025-06-27T09:56:23Z"
    },
    {
      "d": "bioservic.cl",
      "date": "2025-06-27T09:56:09Z"
    },
    {
      "d": "prerana.cl",
      "date": "2025-06-27T09:51:28Z"
    },
    {
      "d": "enevar.cl",
      "date": "2025-06-27T09:49:03Z"
    },
    {
      "d": "gtoys.cl",
      "date": "2025-06-27T09:46:06Z"
    },
    {
      "d": "enervar.cl",
      "date": "2025-06-27T09:44:17Z"
    },
    {
      "d": "mundoadocretos.cl",
      "date": "2025-06-27T09:31:45Z"
    },
    {
      "d": "fatalpermisologia.cl",
      "date": "2025-06-27T09:30:45Z"
    },
    {
      "d": "amaiaritual.cl",
      "date": "2025-06-27T09:29:22Z"
    },
    {
      "d": "disponiblesya.cl",
      "date": "2025-06-27T09:14:54Z"
    },
    {
      "d": "polloya.cl",
      "date": "2025-06-27T09:11:00Z"
    },
    {
      "d": "vibes.cl",
      "date": "2025-06-27T09:06:17Z"
    },
    {
      "d": "tabula-chile.cl",
      "date": "2025-06-27T09:05:43Z"
    },
    {
      "d": "circulolatam.cl",
      "date": "2025-06-27T09:04:35Z"
    },
    {
      "d": "auraclinic.cl",
      "date": "2025-06-27T09:02:11Z"
    },
    {
      "d": "serveracredes.cl",
      "date": "2025-06-27T08:58:47Z"
    },
    {
      "d": "izabelleycristian.cl",
      "date": "2025-06-27T08:55:20Z"
    },
    {
      "d": "f94.cl",
      "date": "2025-06-27T08:52:07Z"
    },
    {
      "d": "larecetapasteleria.cl",
      "date": "2025-06-27T08:51:47Z"
    },
    {
      "d": "clinicaveterinariavidas.cl",
      "date": "2025-06-27T08:39:49Z"
    },
    {
      "d": "cerveceriaquillon.cl",
      "date": "2025-06-27T08:20:51Z"
    },
    {
      "d": "cerveceriacayumanque.cl",
      "date": "2025-06-27T08:16:31Z"
    },
    {
      "d": "sncmail.cl",
      "date": "2025-06-27T08:10:36Z"
    },
    {
      "d": "containa.cl",
      "date": "2025-06-27T08:06:28Z"
    },
    {
      "d": "jugabet-sports.cl",
      "date": "2025-06-27T08:06:20Z"
    },
    {
      "d": "jugabetsports.cl",
      "date": "2025-06-27T08:06:15Z"
    },
    {
      "d": "jugabet-sport.cl",
      "date": "2025-06-27T08:06:10Z"
    },
    {
      "d": "jugabetsport.cl",
      "date": "2025-06-27T08:06:05Z"
    },
    {
      "d": "entropia.cl",
      "date": "2025-06-27T08:02:35Z"
    },
    {
      "d": "hud.cl",
      "date": "2025-06-27T07:54:40Z"
    },
    {
      "d": "musictribu.cl",
      "date": "2025-06-27T07:54:27Z"
    },
    {
      "d": "streetracer.cl",
      "date": "2025-06-27T07:53:40Z"
    },
    {
      "d": "kilowatts.cl",
      "date": "2025-06-27T07:53:39Z"
    },
    {
      "d": "ayudadenisse.cl",
      "date": "2025-06-27T07:52:00Z"
    },
    {
      "d": "mbx.cl",
      "date": "2025-06-27T07:41:02Z"
    }
  ]
}